update_trigger/__init__.py
update_trigger/__main__.py
update_trigger/main.py
update_trigger-0.1.2.dist-info/METADATA
update_trigger-0.1.2.dist-info/WHEEL
update_trigger-0.1.2.dist-info/entry_points.txt
update_trigger-0.1.2.dist-info/top_level.txt
update_trigger-0.1.2.dist-info/RECORD
