Metadata-Version: 2.4
Name: update-trigger
Version: 0.1.2
Summary: Pacote utilizado para publicar mensagens MQTT quando um arquivo é atualizado.
Author-email: Felipe Ribeiro <feliperibeiromachado@edu.univali.br>
License: MIT
Requires-Dist: paho-mqtt==2.1.0
Requires-Dist: python-dotenv==1.1.1
